{
    "COPY_LOCALLY": true,
    "MAIN_TEMP_DIR": "B:\\temp",
    "SUBPROCESS_TIMEOUT": 3600,
    "CHDMAN_NUM_PROCESSORS_MODE": "auto",
    "CHDMAN_NUM_PROCESSORS_MANUAL": 21,
    "CHDMAN_CD_USE_CUSTOM_HUNKS": false,
    "CHDMAN_CD_HUNKS": 18816,
    "CHDMAN_CD_USE_CUSTOM_COMPRESSION": true,
    "CHDMAN_CD_COMPRESSION_TYPES": "cdzs,cdlz,cdfl",
    "CHDMAN_DVD_USE_CUSTOM_HUNKS": false,
    "CHDMAN_DVD_HUNKS": 4096,
    "CHDMAN_DVD_USE_CUSTOM_COMPRESSION": true,
    "CHDMAN_DVD_COMPRESSION_TYPES": "lzma,zstd,huff,flac",
    "CHDMAN_LD_USE_CUSTOM_HUNKS": false,
    "CHDMAN_LD_HUNKS": 4096,
    "CHDMAN_LD_USE_CUSTOM_COMPRESSION": false,
    "CHDMAN_LD_COMPRESSION_TYPES": "avhu",
    "CHDMAN_LD_USE_INPUT_START_FRAME": false,
    "CHDMAN_LD_INPUT_START_FRAME": null,
    "CHDMAN_LD_USE_INPUT_FRAMES": false,
    "CHDMAN_LD_INPUT_FRAMES": null,
    "CHDMAN_HD_USE_CUSTOM_HUNKS": false,
    "CHDMAN_HD_HUNKS": 4096,
    "CHDMAN_HD_USE_CUSTOM_COMPRESSION": true,
    "CHDMAN_HD_COMPRESSION_TYPES": "lzma,zstd,huff,flac",
    "CHDMAN_HD_USE_SECTOR_SIZE": false,
    "CHDMAN_HD_SECTOR_SIZE": null,
    "CHDMAN_HD_USE_SIZE": false,
    "CHDMAN_HD_SIZE": null,
    "CHDMAN_HD_USE_CHS": false,
    "CHDMAN_HD_CHS_C": null,
    "CHDMAN_HD_CHS_H": null,
    "CHDMAN_HD_CHS_S": null,
    "CHDMAN_HD_USE_TEMPLATE": false,
    "CHDMAN_HD_TEMPLATE_PATH": null,
    "CHDMAN_RAW_USE_CUSTOM_HUNKS": false,
    "CHDMAN_RAW_HUNKS": 4096,
    "CHDMAN_RAW_USE_CUSTOM_COMPRESSION": true,
    "CHDMAN_RAW_COMPRESSION_TYPES": "lzma,zstd,huff,flac",
    "CHDMAN_VERIFY_FIX": false,
    "DOLPHINTOOL_RVZ_BLOCKSIZE": 2097152,
    "DOLPHINTOOL_RVZ_COMPRESSION_TYPE": "lzma2",
    "DOLPHINTOOL_RVZ_COMPRESSION_LEVEL": 9,
    "DOLPHINTOOL_WIA_COMPRESSION_TYPE": "none",
    "DOLPHINTOOL_WIA_COMPRESSION_LEVEL": 9,
    "DOLPHINTOOL_GCZ_BLOCKSIZE": 131072,
    "DELETE_SOURCE_ON_SUCCESS": false,
    "VALIDATE_FILE": true,
    "DOLPHIN_COMPRESS_LEVEL": 9
}